Workbook

Sheet Orders_Raw
A1: Order ID | B1: Order Date | C1: Customer ID | D1: Gender | E1: Age | F1: City | G1: Product Category | H1: Product | I1: Quantity | J1: Price per Unit | K1: Total Amount | L1: Discount % | M1: Payment Method | N1: Order Status | O1: Sales Channel | P1: Customer Name
A2: ORD10001 | B2: 45772 | C2: CUST1018 | D2: Male | E2: 52 | F2: Pune | G2: Electronics | H2: Wireless Mouse | I2: 3 | J2: 399 | K2: 1197 | L2: 20 | M2: Cash on Delivery | N2: Delivered | O2: Website | P2: Aditya
A3: ORD10002 | B3: 45671 | C3: CUST1072 | D3: Male | E3: 59 | F3: Aurangabad | G3: Home & Kitchen | H3: Storage Box | I3: 5 | J3: 1499 | K3: 7495 | L3: 5 | M3: Cash on Delivery | N3: Cancelled | O3: Website | P3: Kunal
A4: ORD10003 | B4: 45768 | C4: CUST1098 | D4: Female | E4: 24 | F4: Pune | G4: Beauty | H4: Body Lotion | I4: 3 | J4: 299 | K4: 897 | L4: 15 | M4: UPI | N4: Cancelled | O4: Mobile App | P4: Meera
A5: ORD10004 | B5: 45721 | C5: CUST1049 | D5: Male | E5: 53 | F5: Navi Mumbai | G5: Clothing | H5: T-Shirt | I5: 4 | J5: 1299 | K5: 5196 | L5: 20 | M5: Debit Card | N5: Shipped | O5: Marketplace | P5: Aditya
A6: ORD10005 | B6: 45777 | C6: CUST1013 | D6: Female | E6: 35 | F6: Kolhapur | G6: Electronics | H6: Keyboard | I6: 3 | J6: 249 | K6: 747 | L6: 10 | M6: Credit Card | N6: Cancelled | O6: Mobile App | P6: Akash
A7: ORD10006 | B7: 45745 | C7: CUST1069 | D7: Male | E7: 28 | F7: Kolhapur | G7: Clothing | H7: T-Shirt | I7: 5 | J7: 1999 | K7: 9995 | L7: 15 | M7: Debit Card | N7: Shipped | O7: Marketplace | P7: Ananya
A8: ORD10007 | B8: 45863 | C8: CUST1035 | D8: Male | E8: 31 | F8: Nagpur | G8: Electronics | H8: Keyboard | I8: 1 | J8: 599 | K8: 599 | L8: 5 | M8: Cash on Delivery | N8: Returned | O8: Marketplace | P8: Sneha
A9: ORD10008 | B9: 45945 | C9: CUST1069 | D9: Female | E9: 55 | F9: Aurangabad | G9: Home & Kitchen | H9: Mixer | I9: 2 | J9: 399 | K9: 798 | L9: 20 | M9: Cash on Delivery | N9: Cancelled | O9: Website | P9: Rahul
A10: ORD10009 | B10: 45714 | C10: CUST1020 | D10: Male | E10: 45 | F10: Pune | G10: Grocery | H10: Cooking Oil | I10: 1 | J10: 199 | K10: 199 | L10: 15 | M10: Cash on Delivery | N10: Returned | O10: Marketplace | P10: Yash
A11: ORD10010 | B11: 45932 | C11: CUST1097 | D11: Female | E11: 59 | F11: Nagpur | G11: Grocery | H11: Tea | I11: 1 | J11: 1999 | K11: 1999 | L11: 0 | M11: Debit Card | N11: Returned | O11: Website | P11: Sneha
A12: ORD10011 | B12: 45917 | C12: CUST1014 | D12: Female | E12: 58 | F12: Thane | G12: Electronics | H12: Headphones | I12: 5 | J12: 299 | K12: 1495 | L12: 5 | M12: Debit Card | N12: Shipped | O12: Marketplace | P12: Riya
A13: ORD10012 | B13: 45667 | C13: CUST1015 | D13: Female | E13: 37 | F13: Thane | G13: Electronics | H13: USB Hub | I13: 3 | J13: 999 | K13: 2997 | L13: 0 | M13: Credit Card | N13: Delivered | O13: Website | P13: Pooja
... A501: ORD10500 | B501: 45750 | C501: CUST1092 | D501: Female | E501: 57 | F501: Pune | G501: Home & Kitchen | H501: Cookware Set | I501: 1 | J501: 1499 | K501: 1499 | L501: 10 | M501: Debit Card | N501: Returned | O501: Website | P501: Kavya

Sheet Customer_Master
A1: Customer ID | B1: Customer Name | C1: Customer City | D1: Customer Segment | E1: Account Status
A2: CUST1001 | B2: Sahil | C2: Thane | D2: Regular | E2: Active
A3: CUST1002 | B3: Meera | C3: Nagpur | D3: Silver | E3: Inactive
A4: CUST1003 | B4: Akash | C4: Navi Mumbai | D4: Regular | E4: Active
A5: CUST1004 | B5: Rohan | C5: Nashik | D5: Platinum | E5: Inactive
A6: CUST1005 | B6: Kunal | C6: Nashik | D6: Regular | E6: Active
A7: CUST1006 | B7: Isha | C7: Navi Mumbai | D7: Silver | E7: Inactive
A8: CUST1007 | B8: Yash | C8: Nagpur | D8: Platinum | E8: Active
A9: CUST1008 | B9: Rohan | C9: Mumbai | D9: Silver | E9: Active
A10: CUST1009 | B10: Aarav | C10: Kolhapur | D10: Regular | E10: Active
A11: CUST1010 | B11: Sahil | C11: Kolhapur | D11: Gold | E11: Inactive
A12: CUST1011 | B12: Akash | C12: Nagpur | D12: Silver | E12: Active
... A101: CUST1100 | B101: Riya | C101: Mumbai | D101: Gold | E101: Active

Sheet Product_Master
A1: Product | B1: Category | C1: Standard Price | D1: Price Band
A2: Wireless Mouse | B2: Electronics | C2: 1499 | D2: Low
A3: Keyboard | B3: Electronics | C3: 299 | D3: Medium
A4: Headphones | B4: Electronics | C4: 999 | D4: High
A5: Smart Watch | B5: Electronics | C5: 299 | D5: Medium
A6: USB Hub | B6: Electronics | C6: 299 | D6: Low
A7: Electric Kettle | B7: Home & Kitchen | C7: 499 | D7: Medium
A8: Storage Box | B8: Home & Kitchen | C8: 799 | D8: High
A9: Mixer | B9: Home & Kitchen | C9: 599 | D9: Low
A10: Water Bottle | B10: Home & Kitchen | C10: 499 | D10: Medium
A11: Cookware Set | B11: Home & Kitchen | C11: 1299 | D11: High
A12: T-Shirt | B12: Clothing | C12: 249 | D12: High
A13: Shirt | B13: Clothing | C13: 399 | D13: High
... A26: Dry Fruits | B26: Grocery | C26: 999 | D26: Medium

Sheet Clean_sheet
A1: Order ID | B1: Order Date | C1: Customer ID | D1: Gender | E1: Age | F1: City | G1: Product Category | H1: Product | I1: Quantity | J1: Price per Unit | K1: Total Amount | L1: Discount % | M1: Payment Method | N1: Order Status | O1: Sales Channel | P1: Customer Name
A2: ORD10001 | B2: 45772 | C2: CUST1018 | D2: Male | E2: 52 | F2: Pune | G2: Electronics | H2: Wireless Mouse | I2: 3 | J2: 399 | K2: 1197 | L2: 20 | M2: Cash on Delivery | N2: Delivered | O2: Website | P2: Aditya
A3: ORD10002 | B3: 45671 | C3: CUST1072 | D3: Male | E3: 59 | F3: Aurangabad | G3: Home & Kitchen | H3: Storage Box | I3: 5 | J3: 1499 | K3: 7495 | L3: 5 | M3: Cash on Delivery | N3: Cancelled | O3: Website | P3: Kunal
A4: ORD10003 | B4: 45768 | C4: CUST1098 | D4: Female | E4: 24 | F4: Pune | G4: Beauty | H4: Body Lotion | I4: 3 | J4: 299 | K4: 897 | L4: 15 | M4: UPI | N4: Cancelled | O4: Mobile App | P4: Meera
A5: ORD10004 | B5: 45721 | C5: CUST1049 | D5: Male | E5: 53 | F5: Navi Mumbai | G5: Clothing | H5: T-Shirt | I5: 4 | J5: 1299 | K5: 5196 | L5: 20 | M5: Debit Card | N5: Shipped | O5: Marketplace | P5: Aditya
A6: ORD10005 | B6: 45777 | C6: CUST1013 | D6: Female | E6: 35 | F6: Kolhapur | G6: Electronics | H6: Keyboard | I6: 3 | J6: 249 | K6: 747 | L6: 10 | M6: Credit Card | N6: Cancelled | O6: Mobile App | P6: Akash
A7: ORD10006 | B7: 45745 | C7: CUST1069 | D7: Male | E7: 28 | F7: Kolhapur | G7: Clothing | H7: T-Shirt | I7: 5 | J7: 1999 | K7: 9995 | L7: 15 | M7: Debit Card | N7: Shipped | O7: Marketplace | P7: Ananya
A8: ORD10007 | B8: 45863 | C8: CUST1035 | D8: Male | E8: 31 | F8: Nagpur | G8: Electronics | H8: Keyboard | I8: 1 | J8: 599 | K8: 599 | L8: 5 | M8: Cash on Delivery | N8: Returned | O8: Marketplace | P8: Sneha
A9: ORD10008 | B9: 45945 | C9: CUST1069 | D9: Female | E9: 55 | F9: Aurangabad | G9: Home & Kitchen | H9: Mixer | I9: 2 | J9: 399 | K9: 798 | L9: 20 | M9: Cash on Delivery | N9: Cancelled | O9: Website | P9: Rahul
A10: ORD10009 | B10: 45714 | C10: CUST1020 | D10: Male | E10: 45 | F10: Pune | G10: Grocery | H10: Cooking Oil | I10: 1 | J10: 199 | K10: 199 | L10: 15 | M10: Cash on Delivery | N10: Returned | O10: Marketplace | P10: Yash
A11: ORD10010 | B11: 45932 | C11: CUST1097 | D11: Female | E11: 59 | F11: Nagpur | G11: Grocery | H11: Tea | I11: 1 | J11: 1999 | K11: 1999 | L11: 0 | M11: Debit Card | N11: Returned | O11: Website | P11: Sneha
A12: ORD10011 | B12: 45917 | C12: CUST1014 | D12: Female | E12: 58 | F12: Thane | G12: Electronics | H12: Headphones | I12: 5 | J12: 299 | K12: 1495 | L12: 5 | M12: Debit Card | N12: Shipped | O12: Marketplace | P12: Riya
A13: ORD10012 | B13: 45667 | C13: CUST1015 | D13: Female | E13: 37 | F13: Thane | G13: Electronics | H13: USB Hub | I13: 3 | J13: 999 | K13: 2997 | L13: 0 | M13: Credit Card | N13: Delivered | O13: Website | P13: Pooja
... A501: ORD10500 | B501: 45750 | C501: CUST1092 | D501: Female | E501: 57 | F501: Pune | G501: Home & Kitchen | H501: Cookware Set | I501: 1 | J501: 1499 | K501: 1499 | L501: 10 | M501: Debit Card | N501: Returned | O501: Website | P501: Kavya

Sheet client_formula_data
A1: Xlookup | J1: Countif | M1: Sumif | P1: Sumifs
A4: Customer ID | B4: Customer Segment | C4: Account Status | F4: Product | G4: Standard Price | H4: Price Band | J4: Customer ID | K4: Time to place | M4: Customer ID | N4: Total sale | P4: Category | Q4: City | R4: Total Sales
A5: CUST1018 | B5: =_xlfn.XLOOKUP(A5,Customer_Master!$A$2:$A$101,Customer_Master!$D$2:$D$101) -> Silver | C5: =_xlfn.XLOOKUP(A5,Customer_Master!$A$2:$A$101,Customer_Master!$E$2:$E$101) -> Active | F5: Wireless Mouse | G5: =_xlfn.XLOOKUP(F5,Product_Master!$A$2:$A$26,Product_Master!$C$2:$C$26) -> 1499 | H5: =_xlfn.XLOOKUP(F5,Product_Master!$A$2:$A$26,Product_Master!$D$2:$D$26) -> Low | J5: CUST1018 | K5: {=COUNTIF(Clean_sheet!C2:C501,client_formula_data!A5:A504)} -> 6 | M5: CUST1018 | N5: =SUMIF(Clean_sheet!C2:C501,client_formula_data!M5,Clean_sheet!K2:K501) -> 13778 | P5: {=_xlfn.UNIQUE(Clean_sheet!G2:G501,0)} -> Electronics | Q5: {=_xlfn.UNIQUE(Clean_sheet!F2:F501,0)} -> Pune | R5: =SUMIFS(Clean_sheet!$K$2:$K$501,Clean_sheet!$G$2:$G$501,client_formula_data!P5,Clean_sheet!$F$2:$F$501,client_formula_data!Q5) -> 50459
A6: CUST1072 | B6: =_xlfn.XLOOKUP(A6,Customer_Master!$A$2:$A$101,Customer_Master!$D$2:$D$101) -> Gold | C6: =_xlfn.XLOOKUP(A6,Customer_Master!$A$2:$A$101,Customer_Master!$E$2:$E$101) -> Active | F6: Storage Box | G6: =_xlfn.XLOOKUP(F6,Product_Master!$A$2:$A$26,Product_Master!$C$2:$C$26) -> 799 | H6: =_xlfn.XLOOKUP(F6,Product_Master!$A$2:$A$26,Product_Master!$D$2:$D$26) -> High | J6: CUST1072 | K6: 5 | M6: CUST1072 | N6: =SUMIF(Clean_sheet!C3:C502,client_formula_data!M6,Clean_sheet!K3:K502) -> 23085 | P6: Home & Kitchen | Q6: Aurangabad | R6: =SUMIFS(Clean_sheet!$K$2:$K$501,Clean_sheet!$G$2:$G$501,client_formula_data!P6,Clean_sheet!$F$2:$F$501,client_formula_data!Q6) -> 45698
A7: CUST1098 | B7: =_xlfn.XLOOKUP(A7,Customer_Master!$A$2:$A$101,Customer_Master!$D$2:$D$101) -> Platinum | C7: =_xlfn.XLOOKUP(A7,Customer_Master!$A$2:$A$101,Customer_Master!$E$2:$E$101) -> Inactive | F7: Body Lotion | G7: =_xlfn.XLOOKUP(F7,Product_Master!$A$2:$A$26,Product_Master!$C$2:$C$26) -> 1999 | H7: =_xlfn.XLOOKUP(F7,Product_Master!$A$2:$A$26,Product_Master!$D$2:$D$26) -> High | J7: CUST1098 | K7: 7 | M7: CUST1098 | N7: =SUMIF(Clean_sheet!C4:C503,client_formula_data!M7,Clean_sheet!K4:K503) -> 18176 | P7: Beauty | Q7: Navi Mumbai | R7: =SUMIFS(Clean_sheet!$K$2:$K$501,Clean_sheet!$G$2:$G$501,client_formula_data!P7,Clean_sheet!$F$2:$F$501,client_formula_data!Q7) -> 19870
A8: CUST1049 | B8: =_xlfn.XLOOKUP(A8,Customer_Master!$A$2:$A$101,Customer_Master!$D$2:$D$101) -> Platinum | C8: =_xlfn.XLOOKUP(A8,Customer_Master!$A$2:$A$101,Customer_Master!$E$2:$E$101) -> Active | F8: T-Shirt | G8: =_xlfn.XLOOKUP(F8,Product_Master!$A$2:$A$26,Product_Master!$C$2:$C$26) -> 249 | H8: =_xlfn.XLOOKUP(F8,Product_Master!$A$2:$A$26,Product_Master!$D$2:$D$26) -> High | J8: CUST1049 | K8: 9 | M8: CUST1049 | N8: =SUMIF(Clean_sheet!C5:C504,client_formula_data!M8,Clean_sheet!K5:K504) -> 18176 | P8: Clothing | Q8: Kolhapur | R8: =SUMIFS(Clean_sheet!$K$2:$K$501,Clean_sheet!$G$2:$G$501,client_formula_data!P8,Clean_sheet!$F$2:$F$501,client_formula_data!Q8) -> 59343
A9: CUST1013 | B9: =_xlfn.XLOOKUP(A9,Customer_Master!$A$2:$A$101,Customer_Master!$D$2:$D$101) -> Platinum | C9: =_xlfn.XLOOKUP(A9,Customer_Master!$A$2:$A$101,Customer_Master!$E$2:$E$101) -> Active | F9: Keyboard | G9: =_xlfn.XLOOKUP(F9,Product_Master!$A$2:$A$26,Product_Master!$C$2:$C$26) -> 299 | H9: =_xlfn.XLOOKUP(F9,Product_Master!$A$2:$A$26,Product_Master!$D$2:$D$26) -> Medium | J9: CUST1013 | K9: 4 | M9: CUST1013 | N9: =SUMIF(Clean_sheet!C6:C505,client_formula_data!M9,Clean_sheet!K6:K505) -> 8690 | P9: Grocery | Q9: Nagpur | R9: =SUMIFS(Clean_sheet!$K$2:$K$501,Clean_sheet!$G$2:$G$501,client_formula_data!P9,Clean_sheet!$F$2:$F$501,client_formula_data!Q9) -> 39609
A10: CUST1069 | B10: =_xlfn.XLOOKUP(A10,Customer_Master!$A$2:$A$101,Customer_Master!$D$2:$D$101) -> Regular | C10: =_xlfn.XLOOKUP(A10,Customer_Master!$A$2:$A$101,Customer_Master!$E$2:$E$101) -> Active | F10: T-Shirt | G10: =_xlfn.XLOOKUP(F10,Product_Master!$A$2:$A$26,Product_Master!$C$2:$C$26) -> 249 | H10: =_xlfn.XLOOKUP(F10,Product_Master!$A$2:$A$26,Product_Master!$D$2:$D$26) -> High | J10: CUST1069 | K10: 10 | M10: CUST1069 | N10: =SUMIF(Clean_sheet!C7:C506,client_formula_data!M10,Clean_sheet!K7:K506) -> 27563 | Q10: Thane | R10: =SUMIFS(Clean_sheet!$K$2:$K$501,Clean_sheet!$G$2:$G$501,client_formula_data!P10,Clean_sheet!$F$2:$F$501,client_formula_data!Q10) -> 0
A11: CUST1035 | B11: =_xlfn.XLOOKUP(A11,Customer_Master!$A$2:$A$101,Customer_Master!$D$2:$D$101) -> Platinum | C11: =_xlfn.XLOOKUP(A11,Customer_Master!$A$2:$A$101,Customer_Master!$E$2:$E$101) -> Active | F11: Keyboard | G11: =_xlfn.XLOOKUP(F11,Product_Master!$A$2:$A$26,Product_Master!$C$2:$C$26) -> 299 | H11: =_xlfn.XLOOKUP(F11,Product_Master!$A$2:$A$26,Product_Master!$D$2:$D$26) -> Medium | J11: CUST1035 | K11: 6 | M11: CUST1035 | N11: =SUMIF(Clean_sheet!C8:C507,client_formula_data!M11,Clean_sheet!K8:K507) -> 21182 | Q11: Mumbai | R11: =SUMIFS(Clean_sheet!$K$2:$K$501,Clean_sheet!$G$2:$G$501,client_formula_data!P11,Clean_sheet!$F$2:$F$501,client_formula_data!Q11) -> 0
A12: CUST1069 | B12: =_xlfn.XLOOKUP(A12,Customer_Master!$A$2:$A$101,Customer_Master!$D$2:$D$101) -> Regular | C12: =_xlfn.XLOOKUP(A12,Customer_Master!$A$2:$A$101,Customer_Master!$E$2:$E$101) -> Active | F12: Mixer | G12: =_xlfn.XLOOKUP(F12,Product_Master!$A$2:$A$26,Product_Master!$C$2:$C$26) -> 599 | H12: =_xlfn.XLOOKUP(F12,Product_Master!$A$2:$A$26,Product_Master!$D$2:$D$26) -> Low | J12: CUST1069 | K12: 10 | M12: CUST1069 | N12: =SUMIF(Clean_sheet!C9:C508,client_formula_data!M12,Clean_sheet!K9:K508) -> 17568 | Q12: Nashik | R12: =SUMIFS(Clean_sheet!$K$2:$K$501,Clean_sheet!$G$2:$G$501,client_formula_data!P12,Clean_sheet!$F$2:$F$501,client_formula_data!Q12) -> 0
A13: CUST1020 | B13: =_xlfn.XLOOKUP(A13,Customer_Master!$A$2:$A$101,Customer_Master!$D$2:$D$101) -> Platinum | C13: =_xlfn.XLOOKUP(A13,Customer_Master!$A$2:$A$101,Customer_Master!$E$2:$E$101) -> Inactive | F13: Cooking Oil | G13: =_xlfn.XLOOKUP(F13,Product_Master!$A$2:$A$26,Product_Master!$C$2:$C$26) -> 499 | H13: =_xlfn.XLOOKUP(F13,Product_Master!$A$2:$A$26,Product_Master!$D$2:$D$26) -> Medium | J13: CUST1020 | K13: 3 | M13: CUST1020 | N13: =SUMIF(Clean_sheet!C10:C509,client_formula_data!M13,Clean_sheet!K10:K509) -> 8292
A14: CUST1097 | B14: =_xlfn.XLOOKUP(A14,Customer_Master!$A$2:$A$101,Customer_Master!$D$2:$D$101) -> Platinum | C14: =_xlfn.XLOOKUP(A14,Customer_Master!$A$2:$A$101,Customer_Master!$E$2:$E$101) -> Active | F14: Tea | G14: =_xlfn.XLOOKUP(F14,Product_Master!$A$2:$A$26,Product_Master!$C$2:$C$26) -> 1499 | H14: =_xlfn.XLOOKUP(F14,Product_Master!$A$2:$A$26,Product_Master!$D$2:$D$26) -> Medium | J14: CUST1097 | K14: 6 | M14: CUST1097 | N14: =SUMIF(Clean_sheet!C11:C510,client_formula_data!M14,Clean_sheet!K11:K510) -> 11789
A15: CUST1014 | B15: =_xlfn.XLOOKUP(A15,Customer_Master!$A$2:$A$101,Customer_Master!$D$2:$D$101) -> Platinum | C15: =_xlfn.XLOOKUP(A15,Customer_Master!$A$2:$A$101,Customer_Master!$E$2:$E$101) -> Active | F15: Headphones | G15: =_xlfn.XLOOKUP(F15,Product_Master!$A$2:$A$26,Product_Master!$C$2:$C$26) -> 999 | H15: =_xlfn.XLOOKUP(F15,Product_Master!$A$2:$A$26,Product_Master!$D$2:$D$26) -> High | J15: CUST1014 | K15: 11 | M15: CUST1014 | N15: =SUMIF(Clean_sheet!C12:C511,client_formula_data!M15,Clean_sheet!K12:K511) -> 21467
A16: CUST1015 | B16: =_xlfn.XLOOKUP(A16,Customer_Master!$A$2:$A$101,Customer_Master!$D$2:$D$101) -> Silver | C16: =_xlfn.XLOOKUP(A16,Customer_Master!$A$2:$A$101,Customer_Master!$E$2:$E$101) -> Inactive | F16: USB Hub | G16: =_xlfn.XLOOKUP(F16,Product_Master!$A$2:$A$26,Product_Master!$C$2:$C$26) -> 299 | H16: =_xlfn.XLOOKUP(F16,Product_Master!$A$2:$A$26,Product_Master!$D$2:$D$26) -> Low | J16: CUST1015 | K16: 8 | M16: CUST1015 | N16: =SUMIF(Clean_sheet!C13:C512,client_formula_data!M16,Clean_sheet!K13:K512) -> 21077
A17: CUST1061 | B17: =_xlfn.XLOOKUP(A17,Customer_Master!$A$2:$A$101,Customer_Master!$D$2:$D$101) -> Silver | C17: =_xlfn.XLOOKUP(A17,Customer_Master!$A$2:$A$101,Customer_Master!$E$2:$E$101) -> Inactive | F17: USB Hub | G17: =_xlfn.XLOOKUP(F17,Product_Master!$A$2:$A$26,Product_Master!$C$2:$C$26) -> 299 | H17: =_xlfn.XLOOKUP(F17,Product_Master!$A$2:$A$26,Product_Master!$D$2:$D$26) -> Low | J17: CUST1061 | K17: 4 | M17: CUST1061 | N17: =SUMIF(Clean_sheet!C14:C513,client_formula_data!M17,Clean_sheet!K14:K513) -> 9390
A18: CUST1016 | B18: =_xlfn.XLOOKUP(A18,Customer_Master!$A$2:$A$101,Customer_Master!$D$2:$D$101) -> Gold | C18: =_xlfn.XLOOKUP(A18,Customer_Master!$A$2:$A$101,Customer_Master!$E$2:$E$101) -> Active | F18: Body Lotion | G18: =_xlfn.XLOOKUP(F18,Product_Master!$A$2:$A$26,Product_Master!$C$2:$C$26) -> 1999 | H18: =_xlfn.XLOOKUP(F18,Product_Master!$A$2:$A$26,Product_Master!$D$2:$D$26) -> High | J18: CUST1016 | K18: 6 | M18: CUST1016 | N18: =SUMIF(Clean_sheet!C15:C514,client_formula_data!M18,Clean_sheet!K15:K514) -> 12384
A19: CUST1005 | B19: =_xlfn.XLOOKUP(A19,Customer_Master!$A$2:$A$101,Customer_Master!$D$2:$D$101) -> Regular | C19: =_xlfn.XLOOKUP(A19,Customer_Master!$A$2:$A$101,Customer_Master!$E$2:$E$101) -> Active | F19: Wireless Mouse | G19: =_xlfn.XLOOKUP(F19,Product_Master!$A$2:$A$26,Product_Master!$C$2:$C$26) -> 1499 | H19: =_xlfn.XLOOKUP(F19,Product_Master!$A$2:$A$26,Product_Master!$D$2:$D$26) -> Low | J19: CUST1005 | K19: 5 | M19: CUST1005 | N19: =SUMIF(Clean_sheet!C16:C515,client_formula_data!M19,Clean_sheet!K16:K515) -> 19982
A20: CUST1053 | B20: =_xlfn.XLOOKUP(A20,Customer_Master!$A$2:$A$101,Customer_Master!$D$2:$D$101) -> Gold | C20: =_xlfn.XLOOKUP(A20,Customer_Master!$A$2:$A$101,Customer_Master!$E$2:$E$101) -> Inactive | F20: Dry Fruits | G20: =_xlfn.XLOOKUP(F20,Product_Master!$A$2:$A$26,Product_Master!$C$2:$C$26) -> 999 | H20: =_xlfn.XLOOKUP(F20,Product_Master!$A$2:$A$26,Product_Master!$D$2:$D$26) -> Medium | J20: CUST1053 | K20: 6 | M20: CUST1053 | N20: =SUMIF(Clean_sheet!C17:C516,client_formula_data!M20,Clean_sheet!K17:K516) -> 9781
A21: CUST1014 | B21: =_xlfn.XLOOKUP(A21,Customer_Master!$A$2:$A$101,Customer_Master!$D$2:$D$101) -> Platinum | C21: =_xlfn.XLOOKUP(A21,Customer_Master!$A$2:$A$101,Customer_Master!$E$2:$E$101) -> Active | F21: Wireless Mouse | G21: =_xlfn.XLOOKUP(F21,Product_Master!$A$2:$A$26,Product_Master!$C$2:$C$26) -> 1499 | H21: =_xlfn.XLOOKUP(F21,Product_Master!$A$2:$A$26,Product_Master!$D$2:$D$26) -> Low | J21: CUST1014 | K21: 11 | M21: CUST1014 | N21: =SUMIF(Clean_sheet!C18:C517,client_formula_data!M21,Clean_sheet!K18:K517) -> 19972
A22: CUST1071 | B22: =_xlfn.XLOOKUP(A22,Customer_Master!$A$2:$A$101,Customer_Master!$D$2:$D$101) -> Regular | C22: =_xlfn.XLOOKUP(A22,Customer_Master!$A$2:$A$101,Customer_Master!$E$2:$E$101) -> Inactive | F22: Jacket | G22: =_xlfn.XLOOKUP(F22,Product_Master!$A$2:$A$26,Product_Master!$C$2:$C$26) -> 1499 | H22: =_xlfn.XLOOKUP(F22,Product_Master!$A$2:$A$26,Product_Master!$D$2:$D$26) -> Low | J22: CUST1071 | K22: 9 | M22: CUST1071 | N22: =SUMIF(Clean_sheet!C19:C518,client_formula_data!M22,Clean_sheet!K19:K518) -> 41263
A23: CUST1049 | B23: =_xlfn.XLOOKUP(A23,Customer_Master!$A$2:$A$101,Customer_Master!$D$2:$D$101) -> Platinum | C23: =_xlfn.XLOOKUP(A23,Customer_Master!$A$2:$A$101,Customer_Master!$E$2:$E$101) -> Active | F23: Hair Serum | G23: =_xlfn.XLOOKUP(F23,Product_Master!$A$2:$A$26,Product_Master!$C$2:$C$26) -> 499 | H23: =_xlfn.XLOOKUP(F23,Product_Master!$A$2:$A$26,Product_Master!$D$2:$D$26) -> Medium | J23: CUST1049 | K23: 9 | M23: CUST1049 | N23: =SUMIF(Clean_sheet!C20:C519,client_formula_data!M23,Clean_sheet!K20:K519) -> 12980
A24: CUST1008 | B24: =_xlfn.XLOOKUP(A24,Customer_Master!$A$2:$A$101,Customer_Master!$D$2:$D$101) -> Silver | C24: =_xlfn.XLOOKUP(A24,Customer_Master!$A$2:$A$101,Customer_Master!$E$2:$E$101) -> Active | F24: Hair Serum | G24: =_xlfn.XLOOKUP(F24,Product_Master!$A$2:$A$26,Product_Master!$C$2:$C$26) -> 499 | H24: =_xlfn.XLOOKUP(F24,Product_Master!$A$2:$A$26,Product_Master!$D$2:$D$26) -> Medium | J24: CUST1008 | K24: 6 | M24: CUST1008 | N24: =SUMIF(Clean_sheet!C21:C520,client_formula_data!M24,Clean_sheet!K21:K520) -> 14485
... A104: CUST1044 | B104: =_xlfn.XLOOKUP(A104,Customer_Master!$A$2:$A$101,Customer_Master!$D$2:$D$101) -> Silver | C104: =_xlfn.XLOOKUP(A104,Customer_Master!$A$2:$A$101,Customer_Master!$E$2:$E$101) -> Inactive | F104: Keyboard | G104: =_xlfn.XLOOKUP(F104,Product_Master!$A$2:$A$26,Product_Master!$C$2:$C$26) -> 299 | H104: =_xlfn.XLOOKUP(F104,Product_Master!$A$2:$A$26,Product_Master!$D$2:$D$26) -> Medium | J104: CUST1044 | K104: 6 | M104: CUST1044 | N104: =SUMIF(Clean_sheet!C101:C600,client_formula_data!M104,Clean_sheet!K101:K600) -> 12886
F105: Wireless Mouse | G105: =_xlfn.XLOOKUP(F105,Product_Master!$A$2:$A$26,Product_Master!$C$2:$C$26) -> 1499 | H105: =_xlfn.XLOOKUP(F105,Product_Master!$A$2:$A$26,Product_Master!$D$2:$D$26) -> Low | J105: CUST1054 | K105: 0 | M105: CUST1054 | N105: =SUMIF(Clean_sheet!C102:C601,client_formula_data!M105,Clean_sheet!K102:K601) -> 1995
F106: Wireless Mouse | G106: =_xlfn.XLOOKUP(F106,Product_Master!$A$2:$A$26,Product_Master!$C$2:$C$26) -> 1499 | H106: =_xlfn.XLOOKUP(F106,Product_Master!$A$2:$A$26,Product_Master!$D$2:$D$26) -> Low | J106: CUST1007 | K106: 0 | M106: CUST1007 | N106: =SUMIF(Clean_sheet!C103:C602,client_formula_data!M106,Clean_sheet!K103:K602) -> 23927
F107: Cookware Set | G107: =_xlfn.XLOOKUP(F107,Product_Master!$A$2:$A$26,Product_Master!$C$2:$C$26) -> 1299 | H107: =_xlfn.XLOOKUP(F107,Product_Master!$A$2:$A$26,Product_Master!$D$2:$D$26) -> High | J107: CUST1015 | K107: 0 | M107: CUST1015 | N107: =SUMIF(Clean_sheet!C104:C603,client_formula_data!M107,Clean_sheet!K104:K603) -> 12185
F108: Tea | G108: =_xlfn.XLOOKUP(F108,Product_Master!$A$2:$A$26,Product_Master!$C$2:$C$26) -> 1499 | H108: =_xlfn.XLOOKUP(F108,Product_Master!$A$2:$A$26,Product_Master!$D$2:$D$26) -> Medium | J108: CUST1028 | K108: 0 | M108: CUST1028 | N108: =SUMIF(Clean_sheet!C105:C604,client_formula_data!M108,Clean_sheet!K105:K604) -> 3397
F109: Storage Box | G109: =_xlfn.XLOOKUP(F109,Product_Master!$A$2:$A$26,Product_Master!$C$2:$C$26) -> 799 | H109: =_xlfn.XLOOKUP(F109,Product_Master!$A$2:$A$26,Product_Master!$D$2:$D$26) -> High | J109: CUST1030 | K109: 0 | M109: CUST1030 | N109: =SUMIF(Clean_sheet!C106:C605,client_formula_data!M109,Clean_sheet!K106:K605) -> 21987
F110: Kurta | G110: =_xlfn.XLOOKUP(F110,Product_Master!$A$2:$A$26,Product_Master!$C$2:$C$26) -> 1299 | H110: =_xlfn.XLOOKUP(F110,Product_Master!$A$2:$A$26,Product_Master!$D$2:$D$26) -> Medium | J110: CUST1091 | K110: 0 | M110: CUST1091 | N110: =SUMIF(Clean_sheet!C107:C606,client_formula_data!M110,Clean_sheet!K107:K606) -> 35272
F111: Body Lotion | G111: =_xlfn.XLOOKUP(F111,Product_Master!$A$2:$A$26,Product_Master!$C$2:$C$26) -> 1999 | H111: =_xlfn.XLOOKUP(F111,Product_Master!$A$2:$A$26,Product_Master!$D$2:$D$26) -> High | J111: CUST1032 | K111: 0 | M111: CUST1032 | N111: =SUMIF(Clean_sheet!C108:C607,client_formula_data!M111,Clean_sheet!K108:K607) -> 13086
F112: Mixer | G112: =_xlfn.XLOOKUP(F112,Product_Master!$A$2:$A$26,Product_Master!$C$2:$C$26) -> 599 | H112: =_xlfn.XLOOKUP(F112,Product_Master!$A$2:$A$26,Product_Master!$D$2:$D$26) -> Low | J112: CUST1082 | K112: 0 | M112: CUST1082 | N112: =SUMIF(Clean_sheet!C109:C608,client_formula_data!M112,Clean_sheet!K109:K608) -> 3794
F113: Mixer | G113: =_xlfn.XLOOKUP(F113,Product_Master!$A$2:$A$26,Product_Master!$C$2:$C$26) -> 599 | H113: =_xlfn.XLOOKUP(F113,Product_Master!$A$2:$A$26,Product_Master!$D$2:$D$26) -> Low | J113: CUST1020 | K113: 0 | M113: CUST1020 | N113: =SUMIF(Clean_sheet!C110:C609,client_formula_data!M113,Clean_sheet!K110:K609) -> 8093
F114: Biscuits | G114: =_xlfn.XLOOKUP(F114,Product_Master!$A$2:$A$26,Product_Master!$C$2:$C$26) -> 299 | H114: =_xlfn.XLOOKUP(F114,Product_Master!$A$2:$A$26,Product_Master!$D$2:$D$26) -> High | J114: CUST1009 | K114: 0 | M114: CUST1009 | N114: =SUMIF(Clean_sheet!C111:C610,client_formula_data!M114,Clean_sheet!K111:K610) -> 3891
F115: Headphones | G115: =_xlfn.XLOOKUP(F115,Product_Master!$A$2:$A$26,Product_Master!$C$2:$C$26) -> 999 | H115: =_xlfn.XLOOKUP(F115,Product_Master!$A$2:$A$26,Product_Master!$D$2:$D$26) -> High | J115: CUST1008 | K115: 0 | M115: CUST1008 | N115: =SUMIF(Clean_sheet!C112:C611,client_formula_data!M115,Clean_sheet!K112:K611) -> 8990
F116: Tea | G116: =_xlfn.XLOOKUP(F116,Product_Master!$A$2:$A$26,Product_Master!$C$2:$C$26) -> 1499 | H116: =_xlfn.XLOOKUP(F116,Product_Master!$A$2:$A$26,Product_Master!$D$2:$D$26) -> Medium | J116: CUST1025 | K116: 0 | M116: CUST1025 | N116: =SUMIF(Clean_sheet!C113:C612,client_formula_data!M116,Clean_sheet!K113:K612) -> 13582
... F504: Cookware Set | G504: =_xlfn.XLOOKUP(F504,Product_Master!$A$2:$A$26,Product_Master!$C$2:$C$26) -> 1299 | H504: =_xlfn.XLOOKUP(F504,Product_Master!$A$2:$A$26,Product_Master!$D$2:$D$26) -> High | J504: CUST1092 | K504: 0 | M504: CUST1092 | N504: =SUMIF(Clean_sheet!C501:C1000,client_formula_data!M504,Clean_sheet!K501:K1000) -> 1499
